odoo/addons/auth_saml_groups/README.rst
odoo/addons/auth_saml_groups/__init__.py
odoo/addons/auth_saml_groups/__manifest__.py
odoo/addons/auth_saml_groups/data/auth_saml_groups.xml
odoo/addons/auth_saml_groups/i18n/auth_saml_groups.pot
odoo/addons/auth_saml_groups/models/__init__.py
odoo/addons/auth_saml_groups/models/auth_saml.py
odoo/addons/auth_saml_groups/models/auth_saml_group_mapping.py
odoo/addons/auth_saml_groups/models/auth_saml_operator.py
odoo/addons/auth_saml_groups/models/res_users.py
odoo/addons/auth_saml_groups/readme/CONTRIBUTORS.rst
odoo/addons/auth_saml_groups/readme/CREDITS.rst
odoo/addons/auth_saml_groups/readme/DESCRIPTION.rst
odoo/addons/auth_saml_groups/readme/USAGE.rst
odoo/addons/auth_saml_groups/security/ir.model.access.csv
odoo/addons/auth_saml_groups/static/description/icon.png
odoo/addons/auth_saml_groups/static/description/index.html
odoo/addons/auth_saml_groups/tests/__init__.py
odoo/addons/auth_saml_groups/tests/common.py
odoo/addons/auth_saml_groups/tests/saml_args.py
odoo/addons/auth_saml_groups/tests/test_auth_saml_groups.py
odoo/addons/auth_saml_groups/views/auth_saml.xml
odoo11_addon_auth_saml_groups-11.0.1.0.0.99.dev7.dist-info/METADATA
odoo11_addon_auth_saml_groups-11.0.1.0.0.99.dev7.dist-info/WHEEL
odoo11_addon_auth_saml_groups-11.0.1.0.0.99.dev7.dist-info/top_level.txt
odoo11_addon_auth_saml_groups-11.0.1.0.0.99.dev7.dist-info/RECORD
